dora_pytorch_kinematics/__init__.py
dora_pytorch_kinematics/__main__.py
dora_pytorch_kinematics/main.py
dora_pytorch_kinematics-0.4.1.dist-info/METADATA
dora_pytorch_kinematics-0.4.1.dist-info/WHEEL
dora_pytorch_kinematics-0.4.1.dist-info/entry_points.txt
dora_pytorch_kinematics-0.4.1.dist-info/top_level.txt
dora_pytorch_kinematics-0.4.1.dist-info/RECORD
