Metadata-Version: 2.4
Name: dora-pytorch-kinematics
Version: 0.4.1
Summary: dora-pytorch-kinematics
Author-email: Your Name <email@email.com>
License: MIT
Requires-Python: >=3.10
Requires-Dist: dora-rs>=0.3.9
Requires-Dist: mujoco>=3.2.3
Requires-Dist: pytorch-kinematics>=0.7.5
Requires-Dist: robot-descriptions>=1.17.0
